oiafed/__init__.py
oiafed/__main__.py
oiafed/cli.py
oiafed/runner.py
oiafed/builder/__init__.py
oiafed/builder/builder.py
oiafed/callback/__init__.py
oiafed/callback/base.py
oiafed/callback/builtin.py
oiafed/callback/manager.py
oiafed/callback/sync_callback.py
oiafed/callback/tracker_sync.py
oiafed/comm/README.md
oiafed/comm/__init__.py
oiafed/comm/config.example.yaml
oiafed/comm/config.py
oiafed/comm/exceptions.py
oiafed/comm/message.py
oiafed/comm/node.py
oiafed/comm/interceptor/__init__.py
oiafed/comm/interceptor/auth_interceptor.py
oiafed/comm/interceptor/base.py
oiafed/comm/interceptor/logging_interceptor.py
oiafed/comm/proto/__init__.py
oiafed/comm/proto/node_service.proto
oiafed/comm/proto/node_service_pb2.py
oiafed/comm/proto/node_service_pb2_grpc.py
oiafed/comm/serialization/__init__.py
oiafed/comm/serialization/base.py
oiafed/comm/serialization/json_serializer.py
oiafed/comm/serialization/pickle_serializer.py
oiafed/comm/serialization/registry.py
oiafed/comm/transport/__init__.py
oiafed/comm/transport/base.py
oiafed/comm/transport/factory.py
oiafed/comm/transport/grpc_transport.py
oiafed/comm/transport/memory.py
oiafed/comm/transport/retry.py
oiafed/config/__init__.py
oiafed/config/base.yaml
oiafed/config/manager.py
oiafed/config/types.py
oiafed/core/__init__.py
oiafed/core/aggregator.py
oiafed/core/decorators.py
oiafed/core/learner.py
oiafed/core/model.py
oiafed/core/node.py
oiafed/core/system.py
oiafed/core/trainer.py
oiafed/core/types.py
oiafed/data/__init__.py
oiafed/data/datasets.py
oiafed/data/manager.py
oiafed/data/partitioned_dataset.py
oiafed/data/partitioner.py
oiafed/data/provider.py
oiafed/infra/__init__.py
oiafed/infra/checkpoint.py
oiafed/infra/log_config.py
oiafed/infra/logging.py
oiafed/infra/timer.py
oiafed/infra/tracker.py
oiafed/methods/__init__.py
oiafed/methods/aggregators/__init__.py
oiafed/methods/aggregators/faderaser.py
oiafed/methods/aggregators/fedadam.py
oiafed/methods/aggregators/fedavg.py
oiafed/methods/aggregators/fedbn.py
oiafed-0.2.2.dist-info/METADATA
oiafed-0.2.2.dist-info/WHEEL
oiafed-0.2.2.dist-info/entry_points.txt
oiafed-0.2.2.dist-info/licenses/LICENSE
oiafed-0.2.2.dist-info/RECORD
