Metadata-Version: 2.4
Name: oiafed
Version: 0.2.2
Summary: OiaFed: One Framework for All Federation - A unified, modular, and extensible federated learning framework supporting all federation scenarios
Project-URL: Homepage, https://oiafed.cn
Project-URL: Documentation, https://docs.oiafed.cn
Project-URL: Repository, https://github.com/oiafed/oiafed
Project-URL: Issues, https://github.com/oiafed/oiafed/issues
Project-URL: Changelog, https://github.com/oiafed/oiafed/blob/main/CHANGELOG.md
Author-email: OiaFed Team <contact@oiafed.com>
Maintainer-email: OiaFed Team <contact@oiafed.com>
License: MIT
License-File: LICENSE
Keywords: continual-learning,deep-learning,distributed-computing,federated-learning,machine-learning,personalized-federated-learning,privacy-preserving
Classifier: Development Status :: 4 - Beta
Classifier: Intended Audience :: Developers
Classifier: Intended Audience :: Science/Research
Classifier: License :: OSI Approved :: MIT License
Classifier: Operating System :: OS Independent
Classifier: Programming Language :: Python :: 3
Classifier: Programming Language :: Python :: 3.10
Classifier: Programming Language :: Python :: 3.11
Classifier: Programming Language :: Python :: 3.12
Classifier: Programming Language :: Python :: 3.13
Classifier: Topic :: Scientific/Engineering :: Artificial Intelligence
Classifier: Topic :: System :: Distributed Computing
Requires-Python: >=3.10
Provides-Extra: all
Requires-Dist: black>=22.0.0; extra == 'all'
Requires-Dist: flake8>=5.0.0; extra == 'all'
Requires-Dist: isort>=5.10.0; extra == 'all'
Requires-Dist: mlflow>=2.0.0; extra == 'all'
Requires-Dist: mypy>=0.990; extra == 'all'
Requires-Dist: myst-parser>=0.18.0; extra == 'all'
Requires-Dist: pytest-asyncio>=0.20.0; extra == 'all'
Requires-Dist: pytest-cov>=4.0.0; extra == 'all'
Requires-Dist: pytest-html>=3.2.0; extra == 'all'
Requires-Dist: pytest>=7.0.0; extra == 'all'
Requires-Dist: sphinx-rtd-theme>=1.0.0; extra == 'all'
Requires-Dist: sphinx>=5.0.0; extra == 'all'
Provides-Extra: dependencies
Requires-Dist: aiohttp>=3.8.0; extra == 'dependencies'
Requires-Dist: grpcio-tools>=1.50.0; extra == 'dependencies'
Requires-Dist: grpcio>=1.50.0; extra == 'dependencies'
Requires-Dist: loguru>=0.6.0; extra == 'dependencies'
Requires-Dist: matplotlib>=3.5.0; extra == 'dependencies'
Requires-Dist: numpy>=1.21.0; extra == 'dependencies'
Requires-Dist: omegaconf>=2.2.0; extra == 'dependencies'
Requires-Dist: openpyxl>=3.0.0; extra == 'dependencies'
Requires-Dist: pandas>=1.4.0; extra == 'dependencies'
Requires-Dist: protobuf>=3.20.0; extra == 'dependencies'
Requires-Dist: psutil>=5.9.0; extra == 'dependencies'
Requires-Dist: pyyaml>=6.0; extra == 'dependencies'
Requires-Dist: scikit-learn>=1.0.0; extra == 'dependencies'
Requires-Dist: toml>=0.10.0; extra == 'dependencies'
Requires-Dist: torch>=1.12.0; extra == 'dependencies'
Requires-Dist: torchaudio>=0.12.0; extra == 'dependencies'
Requires-Dist: torchvision>=0.13.0; extra == 'dependencies'
Requires-Dist: tqdm>=4.60.0; extra == 'dependencies'
Provides-Extra: dev
Requires-Dist: black>=22.0.0; extra == 'dev'
Requires-Dist: flake8>=5.0.0; extra == 'dev'
Requires-Dist: isort>=5.10.0; extra == 'dev'
Requires-Dist: mypy>=0.990; extra == 'dev'
Requires-Dist: pytest-asyncio>=0.20.0; extra == 'dev'
Requires-Dist: pytest-cov>=4.0.0; extra == 'dev'
Requires-Dist: pytest-html>=3.2.0; extra == 'dev'
Requires-Dist: pytest>=7.0.0; extra == 'dev'
Provides-Extra: docs
Requires-Dist: myst-parser>=0.18.0; extra == 'docs'
Requires-Dist: sphinx-rtd-theme>=1.0.0; extra == 'docs'
Requires-Dist: sphinx>=5.0.0; extra == 'docs'
Provides-Extra: mlflow
Requires-Dist: mlflow>=2.0.0; extra == 'mlflow'
